robotframework_find_unused/__init__.py
robotframework_find_unused/__main__.py
robotframework_find_unused/cli.py
robotframework_find_unused/commands/__init__.py
robotframework_find_unused/commands/arguments.py
robotframework_find_unused/commands/files.py
robotframework_find_unused/commands/keywords.py
robotframework_find_unused/commands/returns.py
robotframework_find_unused/commands/step/__init__.py
robotframework_find_unused/commands/step/discover_files.py
robotframework_find_unused/commands/step/file_import_filter.py
robotframework_find_unused/commands/step/file_import_tree.py
robotframework_find_unused/commands/step/keyword_count_uses.py
robotframework_find_unused/commands/step/keyword_definitions.py
robotframework_find_unused/commands/step/keyword_filter.py
robotframework_find_unused/commands/step/lib_keyword_definitions.py
robotframework_find_unused/commands/step/parse_file_use.py
robotframework_find_unused/commands/step/parse_files.py
robotframework_find_unused/commands/step/variables_count_uses.py
robotframework_find_unused/commands/step/variables_definitions.py
robotframework_find_unused/commands/variables.py
robotframework_find_unused/common/__init__.py
robotframework_find_unused/common/cli.py
robotframework_find_unused/common/const.py
robotframework_find_unused/common/convert.py
robotframework_find_unused/common/enrich_python_keywords.py
robotframework_find_unused/common/impossible_state_error.py
robotframework_find_unused/common/normalize.py
robotframework_find_unused/common/parse.py
robotframework_find_unused/common/sort.py
robotframework_find_unused/common/visit.py
robotframework_find_unused/visitors/__init__.py
robotframework_find_unused/visitors/file_import.py
robotframework_find_unused/visitors/keyword_visitor.py
robotframework_find_unused/visitors/library_import.py
robotframework_find_unused/visitors/python_keyword_visitor.py
robotframework_find_unused/visitors/variable_count.py
robotframework_find_unused/visitors/variable_definition.py
robotframework_find_unused-0.5.0.dist-info/licenses/LICENSE
robotframework_find_unused-0.5.0.dist-info/WHEEL
robotframework_find_unused-0.5.0.dist-info/entry_points.txt
robotframework_find_unused-0.5.0.dist-info/METADATA
robotframework_find_unused-0.5.0.dist-info/RECORD
