Metadata-Version: 2.4
Name: robotframework-find-unused
Version: 0.5.0
Summary: Find unused parts of your Robot Framework project
Author: Sander van Beek
License-Expression: MIT
License-File: LICENSE
Classifier: Framework :: Robot Framework
Classifier: Framework :: Robot Framework :: Tool
Classifier: Development Status :: 4 - Beta
Classifier: Typing :: Typed
Requires-Dist: click>=8.1.7,<9.0.0
Requires-Dist: robotframework>=6.1.1
Requires-Dist: robotframework-robocop>=6.0.0
Requires-Python: >=3.10
Project-URL: Homepage, https://github.com/Lakitna/robotframework-find-unused
Project-URL: Repository, https://github.com/Lakitna/robotframework-find-unused
